Metadata-Version: 2.1
Name: odoo12-addon-hr-attendance-modification-tracking
Version: 12.0.2.0.1
Summary: Attendance changes will now be registered in the chatter.
Home-page: https://github.com/OCA/hr
Author: Creu Blanca, Landoo, Odoo Community Association (OCA)
Author-email: support@odoo-community.org
License: AGPL-3
Platform: UNKNOWN
Classifier: Programming Language :: Python
Classifier: Framework :: Odoo
Classifier: License :: OSI Approved :: GNU Affero General Public License v3
Requires-Python: >=3.5
Requires-Dist: odoo (<12.1dev,>=12.0a)
